<?xml version="1.0" encoding="UTF-8"?>

<root>
   <sentence>METHODS@:@The@effects@of@OT@on@IP3@formation@and@OT@receptor@levels@were@determined@in@the@myometria@of@non-pregnant@rabbits@,@Days@26@,@28@and@30@of@pregnancy@rabbits@,@postpartum@rabbits@within@12@hours@and@steroid-treated@ovariectomized@rabbits@</sentence>
   <tags>
      <tag pos="6">OT</tag>
      <tag pos="8">IP3</tag>
   </tags>
   <Taggedwords>
      <taggedword index="1" part-of-speech="NNP">METHODS</taggedword>
      <taggedword index="2" part-of-speech=":">:</taggedword>
      <taggedword index="3" part-of-speech="DT">The</taggedword>
      <taggedword index="4" part-of-speech="NNS">effects</taggedword>
      <taggedword index="5" part-of-speech="IN">of</taggedword>
      <taggedword index="6" part-of-speech="NNP">OT</taggedword>
      <taggedword index="7" part-of-speech="IN">on</taggedword>
      <taggedword index="8" part-of-speech="JJ">IP3</taggedword>
      <taggedword index="9" part-of-speech="NN">formation</taggedword>
      <taggedword index="10" part-of-speech="CC">and</taggedword>
      <taggedword index="11" part-of-speech="NNP">OT</taggedword>
      <taggedword index="12" part-of-speech="NN">receptor</taggedword>
      <taggedword index="13" part-of-speech="NNS">levels</taggedword>
      <taggedword index="14" part-of-speech="VBD">were</taggedword>
      <taggedword index="15" part-of-speech="VBN">determined</taggedword>
      <taggedword index="16" part-of-speech="IN">in</taggedword>
      <taggedword index="17" part-of-speech="DT">the</taggedword>
      <taggedword index="18" part-of-speech="NN">myometria</taggedword>
      <taggedword index="19" part-of-speech="IN">of</taggedword>
      <taggedword index="20" part-of-speech="JJ">non-pregnant</taggedword>
      <taggedword index="21" part-of-speech="NNS">rabbits</taggedword>
      <taggedword index="22" part-of-speech=",">,</taggedword>
      <taggedword index="23" part-of-speech="NNP">Days</taggedword>
      <taggedword index="24" part-of-speech="CD">26</taggedword>
      <taggedword index="25" part-of-speech=",">,</taggedword>
      <taggedword index="26" part-of-speech="CD">28</taggedword>
      <taggedword index="27" part-of-speech="CC">and</taggedword>
      <taggedword index="28" part-of-speech="CD">30</taggedword>
      <taggedword index="29" part-of-speech="IN">of</taggedword>
      <taggedword index="30" part-of-speech="NN">pregnancy</taggedword>
      <taggedword index="31" part-of-speech="NNS">rabbits</taggedword>
      <taggedword index="32" part-of-speech=",">,</taggedword>
      <taggedword index="33" part-of-speech="NN">postpartum</taggedword>
      <taggedword index="34" part-of-speech="NNS">rabbits</taggedword>
      <taggedword index="35" part-of-speech="IN">within</taggedword>
      <taggedword index="36" part-of-speech="CD">12</taggedword>
      <taggedword index="37" part-of-speech="NNS">hours</taggedword>
      <taggedword index="38" part-of-speech="CC">and</taggedword>
      <taggedword index="39" part-of-speech="JJ">steroid-treated</taggedword>
      <taggedword index="40" part-of-speech="JJ">ovariectomized</taggedword>
      <taggedword index="41" part-of-speech="NNS">rabbits</taggedword>
   </Taggedwords>
   <dependencies>
      <dependency dep="METHODS" dep_index="1" gov="ROOT" gov_index="0">root</dependency>
      <dependency dep="The" dep_index="3" gov="effects" gov_index="4">det</dependency>
      <dependency dep="effects" dep_index="4" gov="determined" gov_index="15">nsubjpass</dependency>
      <dependency dep="OT" dep_index="6" gov="effects" gov_index="4">prep_of</dependency>
      <dependency dep="IP3" dep_index="8" gov="formation" gov_index="9">amod</dependency>
      <dependency dep="formation" dep_index="9" gov="OT" gov_index="6">prep_on</dependency>
      <dependency dep="OT" dep_index="11" gov="levels" gov_index="13">nn</dependency>
      <dependency dep="receptor" dep_index="12" gov="levels" gov_index="13">nn</dependency>
      <dependency dep="levels" dep_index="13" gov="OT" gov_index="6">prep_on</dependency>
      <dependency dep="levels" dep_index="13" gov="formation" gov_index="9">conj_and</dependency>
      <dependency dep="were" dep_index="14" gov="determined" gov_index="15">auxpass</dependency>
      <dependency dep="determined" dep_index="15" gov="METHODS" gov_index="1">dep</dependency>
      <dependency dep="the" dep_index="17" gov="myometria" gov_index="18">det</dependency>
      <dependency dep="myometria" dep_index="18" gov="determined" gov_index="15">prep_in</dependency>
      <dependency dep="non-pregnant" dep_index="20" gov="rabbits" gov_index="21">amod</dependency>
      <dependency dep="rabbits" dep_index="21" gov="myometria" gov_index="18">prep_of</dependency>
      <dependency dep="Days" dep_index="23" gov="myometria" gov_index="18">appos</dependency>
      <dependency dep="26" dep_index="24" gov="Days" gov_index="23">num</dependency>
      <dependency dep="28" dep_index="26" gov="Days" gov_index="23">num</dependency>
      <dependency dep="30" dep_index="28" gov="myometria" gov_index="18">appos</dependency>
      <dependency dep="30" dep_index="28" gov="Days" gov_index="23">conj_and</dependency>
      <dependency dep="pregnancy" dep_index="30" gov="rabbits" gov_index="31">nn</dependency>
      <dependency dep="rabbits" dep_index="31" gov="Days" gov_index="23">prep_of</dependency>
      <dependency dep="postpartum" dep_index="33" gov="rabbits" gov_index="34">nn</dependency>
      <dependency dep="rabbits" dep_index="34" gov="myometria" gov_index="18">appos</dependency>
      <dependency dep="12" dep_index="36" gov="hours" gov_index="37">num</dependency>
      <dependency dep="hours" dep_index="37" gov="rabbits" gov_index="34">prep_within</dependency>
      <dependency dep="steroid-treated" dep_index="39" gov="rabbits" gov_index="41">amod</dependency>
      <dependency dep="ovariectomized" dep_index="40" gov="rabbits" gov_index="41">amod</dependency>
      <dependency dep="rabbits" dep_index="41" gov="rabbits" gov_index="34">prep_within</dependency>
      <dependency dep="rabbits" dep_index="41" gov="hours" gov_index="37">conj_and</dependency>
   </dependencies>
   <relations>
      <relation position="600008" relationship="false"></relation>
   </relations>
   <pairs/>
</root>
